{
  "lastUpdated": "2026-04-09T13:27:16.463Z",
  "platforms": {
    "twitter": {
      "name": "X (Twitter)",
      "icon": "𝕏",
      "items": [
        {
          "rank": 1,
          "title": "101 LOVE BY TEETEE",
          "url": "https://twitter.com/search?q=101%20LOVE%20BY%20TEETEE",
          "hot": "",
          "platform": "twitter"
        },
        {
          "rank": 2,
          "title": "#素のまんま",
          "url": "https://twitter.com/search?q=%23%E7%B4%A0%E3%81%AE%E3%81%BE%E3%82%93%E3%81%BE",
          "hot": "",
          "platform": "twitter"
        },
        {
          "rank": 3,
          "title": "#リエラ生放送",
          "url": "https://twitter.com/search?q=%23%E3%83%AA%E3%82%A8%E3%83%A9%E7%94%9F%E6%94%BE%E9%80%81",
          "hot": "",
          "platform": "twitter"
        },
        {
          "rank": 4,
          "title": "#MCMTHxTleFirstone",
          "url": "https://twitter.com/search?q=%23MCMTHxTleFirstone",
          "hot": "",
          "platform": "twitter"
        },
        {
          "rank": 5,
          "title": "#MCMThailand",
          "url": "https://twitter.com/search?q=%23MCMThailand",
          "hot": "",
          "platform": "twitter"
        },
        {
          "rank": 6,
          "title": "コールド",
          "url": "https://twitter.com/search?q=%E3%82%B3%E3%83%BC%E3%83%AB%E3%83%89",
          "hot": "",
          "platform": "twitter"
        },
        {
          "rank": 7,
          "title": "COME OVER",
          "url": "https://twitter.com/search?q=COME%20OVER",
          "hot": "",
          "platform": "twitter"
        },
        {
          "rank": 8,
          "title": "I NEED U",
          "url": "https://twitter.com/search?q=I%20NEED%20U",
          "hot": "",
          "platform": "twitter"
        },
        {
          "rank": 9,
          "title": "INTO THE SUN",
          "url": "https://twitter.com/search?q=INTO%20THE%20SUN",
          "hot": "",
          "platform": "twitter"
        },
        {
          "rank": 10,
          "title": "#AnantSeva",
          "url": "https://twitter.com/search?q=%23AnantSeva",
          "hot": "",
          "platform": "twitter"
        },
        {
          "rank": 11,
          "title": "たかほー",
          "url": "https://twitter.com/search?q=%E3%81%9F%E3%81%8B%E3%81%BB%E3%83%BC",
          "hot": "",
          "platform": "twitter"
        },
        {
          "rank": 12,
          "title": "茨木くん",
          "url": "https://twitter.com/search?q=%E8%8C%A8%E6%9C%A8%E3%81%8F%E3%82%93",
          "hot": "",
          "platform": "twitter"
        },
        {
          "rank": 13,
          "title": "ひょうたん",
          "url": "https://twitter.com/search?q=%E3%81%B2%E3%82%87%E3%81%86%E3%81%9F%E3%82%93",
          "hot": "",
          "platform": "twitter"
        },
        {
          "rank": 14,
          "title": "ミニストップ",
          "url": "https://twitter.com/search?q=%E3%83%9F%E3%83%8B%E3%82%B9%E3%83%88%E3%83%83%E3%83%97",
          "hot": "",
          "platform": "twitter"
        },
        {
          "rank": 15,
          "title": "みっちゃんセンター",
          "url": "https://twitter.com/search?q=%E3%81%BF%E3%81%A3%E3%81%A1%E3%82%83%E3%82%93%E3%82%BB%E3%83%B3%E3%82%BF%E3%83%BC",
          "hot": "",
          "platform": "twitter"
        },
        {
          "rank": 16,
          "title": "ラブシャ",
          "url": "https://twitter.com/search?q=%E3%83%A9%E3%83%96%E3%82%B7%E3%83%A3",
          "hot": "",
          "platform": "twitter"
        },
        {
          "rank": 17,
          "title": "NOT TODAY",
          "url": "https://twitter.com/search?q=NOT%20TODAY",
          "hot": "",
          "platform": "twitter"
        },
        {
          "rank": 18,
          "title": "JS CEAN WATER FEST",
          "url": "https://twitter.com/search?q=JS%20CEAN%20WATER%20FEST",
          "hot": "",
          "platform": "twitter"
        },
        {
          "rank": 19,
          "title": "エビライ",
          "url": "https://twitter.com/search?q=%E3%82%A8%E3%83%93%E3%83%A9%E3%82%A4",
          "hot": "",
          "platform": "twitter"
        },
        {
          "rank": 20,
          "title": "ウレーニャ",
          "url": "https://twitter.com/search?q=%E3%82%A6%E3%83%AC%E3%83%BC%E3%83%8B%E3%83%A3",
          "hot": "",
          "platform": "twitter"
        },
        {
          "rank": 21,
          "title": "茨木初勝利",
          "url": "https://twitter.com/search?q=%E8%8C%A8%E6%9C%A8%E5%88%9D%E5%8B%9D%E5%88%A9",
          "hot": "",
          "platform": "twitter"
        },
        {
          "rank": 22,
          "title": "I NEED YOU",
          "url": "https://twitter.com/search?q=I%20NEED%20YOU",
          "hot": "",
          "platform": "twitter"
        },
        {
          "rank": 23,
          "title": "One More Night",
          "url": "https://twitter.com/search?q=One%20More%20Night",
          "hot": "",
          "platform": "twitter"
        },
        {
          "rank": 24,
          "title": "MRS FM PRESS TOUR",
          "url": "https://twitter.com/search?q=MRS%20FM%20PRESS%20TOUR",
          "hot": "",
          "platform": "twitter"
        },
        {
          "rank": 25,
          "title": "茨木投手",
          "url": "https://twitter.com/search?q=%E8%8C%A8%E6%9C%A8%E6%8A%95%E6%89%8B",
          "hot": "",
          "platform": "twitter"
        },
        {
          "rank": 26,
          "title": "STAGE GENIUS V",
          "url": "https://twitter.com/search?q=STAGE%20GENIUS%20V",
          "hot": "",
          "platform": "twitter"
        },
        {
          "rank": 27,
          "title": "FAKE LOVE",
          "url": "https://twitter.com/search?q=FAKE%20LOVE",
          "hot": "",
          "platform": "twitter"
        },
        {
          "rank": 28,
          "title": "RYO HAIR LIVE KNP",
          "url": "https://twitter.com/search?q=RYO%20HAIR%20LIVE%20KNP",
          "hot": "",
          "platform": "twitter"
        },
        {
          "rank": 29,
          "title": "ノーアウト満塁",
          "url": "https://twitter.com/search?q=%E3%83%8E%E3%83%BC%E3%82%A2%E3%82%A6%E3%83%88%E6%BA%80%E5%A1%81",
          "hot": "",
          "platform": "twitter"
        },
        {
          "rank": 30,
          "title": "キラーチューン",
          "url": "https://twitter.com/search?q=%E3%82%AD%E3%83%A9%E3%83%BC%E3%83%81%E3%83%A5%E3%83%BC%E3%83%B3",
          "hot": "",
          "platform": "twitter"
        }
      ]
    },
    "bilibili": {
      "name": "Bilibili",
      "icon": "📺",
      "items": [
        {
          "rank": 1,
          "title": "sbti人格测试火了",
          "url": "https://search.bilibili.com/all?keyword=sbti%E4%BA%BA%E6%A0%BC%E6%B5%8B%E8%AF%95%E7%81%AB%E4%BA%86&from_source=webtop_search",
          "hot": "",
          "platform": "bilibili"
        },
        {
          "rank": 2,
          "title": "BLG WE",
          "url": "https://search.bilibili.com/all?keyword=BLG+WE&from_source=webtop_search",
          "hot": "",
          "platform": "bilibili"
        },
        {
          "rank": 3,
          "title": "归期妈妈谈送儿子打电竞",
          "url": "https://search.bilibili.com/all?keyword=%E5%BD%92%E6%9C%9F%E5%A6%88%E5%A6%88%E8%B0%88%E9%80%81%E5%84%BF%E5%AD%90%E6%89%93%E7%94%B5%E7%AB%9E&from_source=webtop_search",
          "hot": "",
          "platform": "bilibili"
        },
        {
          "rank": 4,
          "title": "檀健次演唱会大电影",
          "url": "https://search.bilibili.com/all?keyword=%E6%AA%80%E5%81%A5%E6%AC%A1%E6%BC%94%E5%94%B1%E4%BC%9A%E5%A4%A7%E7%94%B5%E5%BD%B1&from_source=webtop_search",
          "hot": "",
          "platform": "bilibili"
        },
        {
          "rank": 5,
          "title": "国防部回应日本部署远程导弹",
          "url": "https://search.bilibili.com/all?keyword=%E5%9B%BD%E9%98%B2%E9%83%A8%E5%9B%9E%E5%BA%94%E6%97%A5%E6%9C%AC%E9%83%A8%E7%BD%B2%E8%BF%9C%E7%A8%8B%E5%AF%BC%E5%BC%B9&from_source=webtop_search",
          "hot": "",
          "platform": "bilibili"
        },
        {
          "rank": 6,
          "title": "虚假摆拍深山救助流浪女 3人被查",
          "url": "https://search.bilibili.com/all?keyword=%E8%99%9A%E5%81%87%E6%91%86%E6%8B%8D%E6%B7%B1%E5%B1%B1%E6%95%91%E5%8A%A9%E6%B5%81%E6%B5%AA%E5%A5%B3+3%E4%BA%BA%E8%A2%AB%E6%9F%A5&from_source=webtop_search",
          "hot": "",
          "platform": "bilibili"
        },
        {
          "rank": 7,
          "title": "美前高官称防止以方破坏停火",
          "url": "https://search.bilibili.com/all?keyword=%E7%BE%8E%E5%89%8D%E9%AB%98%E5%AE%98%E7%A7%B0%E9%98%B2%E6%AD%A2%E4%BB%A5%E6%96%B9%E7%A0%B4%E5%9D%8F%E5%81%9C%E7%81%AB&from_source=webtop_search",
          "hot": "",
          "platform": "bilibili"
        },
        {
          "rank": 8,
          "title": "Wi-Fi 8有何升级",
          "url": "https://search.bilibili.com/all?keyword=Wi-Fi+8%E6%9C%89%E4%BD%95%E5%8D%87%E7%BA%A7&from_source=webtop_search",
          "hot": "",
          "platform": "bilibili"
        },
        {
          "rank": 9,
          "title": "纯血AI公司的护城河在哪",
          "url": "https://search.bilibili.com/all?keyword=%E7%BA%AF%E8%A1%80AI%E5%85%AC%E5%8F%B8%E7%9A%84%E6%8A%A4%E5%9F%8E%E6%B2%B3%E5%9C%A8%E5%93%AA&from_source=webtop_search",
          "hot": "",
          "platform": "bilibili"
        },
        {
          "rank": 10,
          "title": "浪姐小考越努力越心酸",
          "url": "https://search.bilibili.com/all?keyword=%E6%B5%AA%E5%A7%90%E5%B0%8F%E8%80%83%E8%B6%8A%E5%8A%AA%E5%8A%9B%E8%B6%8A%E5%BF%83%E9%85%B8&from_source=webtop_search",
          "hot": "",
          "platform": "bilibili"
        }
      ]
    },
    "instagram": {
      "name": "Instagram",
      "icon": "📷",
      "items": [
        {
          "rank": 1,
          "title": "#love",
          "url": "https://www.instagram.com/explore/tags/love/",
          "hot": "",
          "platform": "instagram"
        },
        {
          "rank": 2,
          "title": "#instagood",
          "url": "https://www.instagram.com/explore/tags/instagood/",
          "hot": "",
          "platform": "instagram"
        },
        {
          "rank": 3,
          "title": "#fashion",
          "url": "https://www.instagram.com/explore/tags/fashion/",
          "hot": "",
          "platform": "instagram"
        },
        {
          "rank": 4,
          "title": "#photooftheday",
          "url": "https://www.instagram.com/explore/tags/photooftheday/",
          "hot": "",
          "platform": "instagram"
        },
        {
          "rank": 5,
          "title": "#photography",
          "url": "https://www.instagram.com/explore/tags/photography/",
          "hot": "",
          "platform": "instagram"
        },
        {
          "rank": 6,
          "title": "#beautiful",
          "url": "https://www.instagram.com/explore/tags/beautiful/",
          "hot": "",
          "platform": "instagram"
        },
        {
          "rank": 7,
          "title": "#art",
          "url": "https://www.instagram.com/explore/tags/art/",
          "hot": "",
          "platform": "instagram"
        },
        {
          "rank": 8,
          "title": "#picoftheday",
          "url": "https://www.instagram.com/explore/tags/picoftheday/",
          "hot": "",
          "platform": "instagram"
        },
        {
          "rank": 9,
          "title": "#nature",
          "url": "https://www.instagram.com/explore/tags/nature/",
          "hot": "",
          "platform": "instagram"
        },
        {
          "rank": 10,
          "title": "#happy",
          "url": "https://www.instagram.com/explore/tags/happy/",
          "hot": "",
          "platform": "instagram"
        },
        {
          "rank": 11,
          "title": "#follow",
          "url": "https://www.instagram.com/explore/tags/follow/",
          "hot": "",
          "platform": "instagram"
        },
        {
          "rank": 12,
          "title": "#travel",
          "url": "https://www.instagram.com/explore/tags/travel/",
          "hot": "",
          "platform": "instagram"
        },
        {
          "rank": 13,
          "title": "#style",
          "url": "https://www.instagram.com/explore/tags/style/",
          "hot": "",
          "platform": "instagram"
        },
        {
          "rank": 14,
          "title": "#instadaily",
          "url": "https://www.instagram.com/explore/tags/instadaily/",
          "hot": "",
          "platform": "instagram"
        },
        {
          "rank": 15,
          "title": "#reels",
          "url": "https://www.instagram.com/explore/tags/reels/",
          "hot": "",
          "platform": "instagram"
        },
        {
          "rank": 16,
          "title": "#like",
          "url": "https://www.instagram.com/explore/tags/like/",
          "hot": "",
          "platform": "instagram"
        },
        {
          "rank": 17,
          "title": "#fitness",
          "url": "https://www.instagram.com/explore/tags/fitness/",
          "hot": "",
          "platform": "instagram"
        },
        {
          "rank": 18,
          "title": "#life",
          "url": "https://www.instagram.com/explore/tags/life/",
          "hot": "",
          "platform": "instagram"
        },
        {
          "rank": 19,
          "title": "#beauty",
          "url": "https://www.instagram.com/explore/tags/beauty/",
          "hot": "",
          "platform": "instagram"
        },
        {
          "rank": 20,
          "title": "#food",
          "url": "https://www.instagram.com/explore/tags/food/",
          "hot": "",
          "platform": "instagram"
        }
      ]
    },
    "zhihu": {
      "name": "知乎",
      "icon": "💡",
      "items": []
    },
    "baidu": {
      "name": "百度热搜",
      "icon": "🔍",
      "items": [
        {
          "rank": 1,
          "title": "立党为公 心底无私天地宽",
          "url": "https://www.baidu.com/s?wd=%E7%AB%8B%E5%85%9A%E4%B8%BA%E5%85%AC%20%E5%BF%83%E5%BA%95%E6%97%A0%E7%A7%81%E5%A4%A9%E5%9C%B0%E5%AE%BD",
          "hot": "",
          "platform": "baidu"
        },
        {
          "rank": 2,
          "title": "“每天上千条请求 我不敢一一回复”",
          "url": "https://www.baidu.com/s?wd=%E2%80%9C%E6%AF%8F%E5%A4%A9%E4%B8%8A%E5%8D%83%E6%9D%A1%E8%AF%B7%E6%B1%82%20%E6%88%91%E4%B8%8D%E6%95%A2%E4%B8%80%E4%B8%80%E5%9B%9E%E5%A4%8D%E2%80%9D",
          "hot": "",
          "platform": "baidu"
        },
        {
          "rank": 3,
          "title": "2947人的投资群里2946人是“托”",
          "url": "https://www.baidu.com/s?wd=2947%E4%BA%BA%E7%9A%84%E6%8A%95%E8%B5%84%E7%BE%A4%E9%87%8C2946%E4%BA%BA%E6%98%AF%E2%80%9C%E6%89%98%E2%80%9D",
          "hot": "",
          "platform": "baidu"
        },
        {
          "rank": 4,
          "title": "大雾、强对流天气等四预警齐发",
          "url": "https://www.baidu.com/s?wd=%E5%A4%A7%E9%9B%BE%E3%80%81%E5%BC%BA%E5%AF%B9%E6%B5%81%E5%A4%A9%E6%B0%94%E7%AD%89%E5%9B%9B%E9%A2%84%E8%AD%A6%E9%BD%90%E5%8F%91",
          "hot": "",
          "platform": "baidu"
        },
        {
          "rank": 5,
          "title": "又一个千万人口城市要来了",
          "url": "https://www.baidu.com/s?wd=%E5%8F%88%E4%B8%80%E4%B8%AA%E5%8D%83%E4%B8%87%E4%BA%BA%E5%8F%A3%E5%9F%8E%E5%B8%82%E8%A6%81%E6%9D%A5%E4%BA%86",
          "hot": "",
          "platform": "baidu"
        },
        {
          "rank": 6,
          "title": "王毅同朝鲜外相崔善姬举行会谈",
          "url": "https://www.baidu.com/s?wd=%E7%8E%8B%E6%AF%85%E5%90%8C%E6%9C%9D%E9%B2%9C%E5%A4%96%E7%9B%B8%E5%B4%94%E5%96%84%E5%A7%AC%E4%B8%BE%E8%A1%8C%E4%BC%9A%E8%B0%88",
          "hot": "",
          "platform": "baidu"
        },
        {
          "rank": 7,
          "title": "虚假摆拍深山救助流浪女 3人被查",
          "url": "https://www.baidu.com/s?wd=%E8%99%9A%E5%81%87%E6%91%86%E6%8B%8D%E6%B7%B1%E5%B1%B1%E6%95%91%E5%8A%A9%E6%B5%81%E6%B5%AA%E5%A5%B3%203%E4%BA%BA%E8%A2%AB%E6%9F%A5",
          "hot": "",
          "platform": "baidu"
        },
        {
          "rank": 8,
          "title": "伊朗总统警告以色列：勿再侵犯黎巴嫩",
          "url": "https://www.baidu.com/s?wd=%E4%BC%8A%E6%9C%97%E6%80%BB%E7%BB%9F%E8%AD%A6%E5%91%8A%E4%BB%A5%E8%89%B2%E5%88%97%EF%BC%9A%E5%8B%BF%E5%86%8D%E4%BE%B5%E7%8A%AF%E9%BB%8E%E5%B7%B4%E5%AB%A9",
          "hot": "",
          "platform": "baidu"
        },
        {
          "rank": 9,
          "title": "还款5年后发现房贷年利率3.8变8.7",
          "url": "https://www.baidu.com/s?wd=%E8%BF%98%E6%AC%BE5%E5%B9%B4%E5%90%8E%E5%8F%91%E7%8E%B0%E6%88%BF%E8%B4%B7%E5%B9%B4%E5%88%A9%E7%8E%873.8%E5%8F%988.7",
          "hot": "",
          "platform": "baidu"
        },
        {
          "rank": 10,
          "title": "“你那个2米26的同学来了”",
          "url": "https://www.baidu.com/s?wd=%E2%80%9C%E4%BD%A0%E9%82%A3%E4%B8%AA2%E7%B1%B326%E7%9A%84%E5%90%8C%E5%AD%A6%E6%9D%A5%E4%BA%86%E2%80%9D",
          "hot": "",
          "platform": "baidu"
        },
        {
          "rank": 11,
          "title": "刘强东章泽天成立新公司“天强”",
          "url": "https://www.baidu.com/s?wd=%E5%88%98%E5%BC%BA%E4%B8%9C%E7%AB%A0%E6%B3%BD%E5%A4%A9%E6%88%90%E7%AB%8B%E6%96%B0%E5%85%AC%E5%8F%B8%E2%80%9C%E5%A4%A9%E5%BC%BA%E2%80%9D",
          "hot": "",
          "platform": "baidu"
        },
        {
          "rank": 12,
          "title": "人社部辟谣发放2026年度综合补贴",
          "url": "https://www.baidu.com/s?wd=%E4%BA%BA%E7%A4%BE%E9%83%A8%E8%BE%9F%E8%B0%A3%E5%8F%91%E6%94%BE2026%E5%B9%B4%E5%BA%A6%E7%BB%BC%E5%90%88%E8%A1%A5%E8%B4%B4",
          "hot": "",
          "platform": "baidu"
        },
        {
          "rank": 13,
          "title": "伊朗伊斯兰革命卫队：复仇不会停止",
          "url": "https://www.baidu.com/s?wd=%E4%BC%8A%E6%9C%97%E4%BC%8A%E6%96%AF%E5%85%B0%E9%9D%A9%E5%91%BD%E5%8D%AB%E9%98%9F%EF%BC%9A%E5%A4%8D%E4%BB%87%E4%B8%8D%E4%BC%9A%E5%81%9C%E6%AD%A2",
          "hot": "",
          "platform": "baidu"
        },
        {
          "rank": 14,
          "title": "安徽：坚决拥护党中央决定",
          "url": "https://www.baidu.com/s?wd=%E5%AE%89%E5%BE%BD%EF%BC%9A%E5%9D%9A%E5%86%B3%E6%8B%A5%E6%8A%A4%E5%85%9A%E4%B8%AD%E5%A4%AE%E5%86%B3%E5%AE%9A",
          "hot": "",
          "platform": "baidu"
        },
        {
          "rank": 15,
          "title": "800斤黄牛坠洞 主人营救4天无奈放弃",
          "url": "https://www.baidu.com/s?wd=800%E6%96%A4%E9%BB%84%E7%89%9B%E5%9D%A0%E6%B4%9E%20%E4%B8%BB%E4%BA%BA%E8%90%A5%E6%95%914%E5%A4%A9%E6%97%A0%E5%A5%88%E6%94%BE%E5%BC%83",
          "hot": "",
          "platform": "baidu"
        },
        {
          "rank": 16,
          "title": "武汉杨泗港长江大桥再现“雨帘瀑布”",
          "url": "https://www.baidu.com/s?wd=%E6%AD%A6%E6%B1%89%E6%9D%A8%E6%B3%97%E6%B8%AF%E9%95%BF%E6%B1%9F%E5%A4%A7%E6%A1%A5%E5%86%8D%E7%8E%B0%E2%80%9C%E9%9B%A8%E5%B8%98%E7%80%91%E5%B8%83%E2%80%9D",
          "hot": "",
          "platform": "baidu"
        },
        {
          "rank": 17,
          "title": "打赏近300万 主播竟是20岁孩子的妈",
          "url": "https://www.baidu.com/s?wd=%E6%89%93%E8%B5%8F%E8%BF%91300%E4%B8%87%20%E4%B8%BB%E6%92%AD%E7%AB%9F%E6%98%AF20%E5%B2%81%E5%AD%A9%E5%AD%90%E7%9A%84%E5%A6%88",
          "hot": "",
          "platform": "baidu"
        },
        {
          "rank": 18,
          "title": "这些高危人群建议尽早做胃镜",
          "url": "https://www.baidu.com/s?wd=%E8%BF%99%E4%BA%9B%E9%AB%98%E5%8D%B1%E4%BA%BA%E7%BE%A4%E5%BB%BA%E8%AE%AE%E5%B0%BD%E6%97%A9%E5%81%9A%E8%83%83%E9%95%9C",
          "hot": "",
          "platform": "baidu"
        },
        {
          "rank": 19,
          "title": "男子吃大量山楂胃里长8厘米“巨石”",
          "url": "https://www.baidu.com/s?wd=%E7%94%B7%E5%AD%90%E5%90%83%E5%A4%A7%E9%87%8F%E5%B1%B1%E6%A5%82%E8%83%83%E9%87%8C%E9%95%BF8%E5%8E%98%E7%B1%B3%E2%80%9C%E5%B7%A8%E7%9F%B3%E2%80%9D",
          "hot": "",
          "platform": "baidu"
        },
        {
          "rank": 20,
          "title": "陌生大妈婚礼抢喜被伴娘一把摁住",
          "url": "https://www.baidu.com/s?wd=%E9%99%8C%E7%94%9F%E5%A4%A7%E5%A6%88%E5%A9%9A%E7%A4%BC%E6%8A%A2%E5%96%9C%E8%A2%AB%E4%BC%B4%E5%A8%98%E4%B8%80%E6%8A%8A%E6%91%81%E4%BD%8F",
          "hot": "",
          "platform": "baidu"
        },
        {
          "rank": 21,
          "title": "被张家界天门山的机器人硬控住了",
          "url": "https://www.baidu.com/s?wd=%E8%A2%AB%E5%BC%A0%E5%AE%B6%E7%95%8C%E5%A4%A9%E9%97%A8%E5%B1%B1%E7%9A%84%E6%9C%BA%E5%99%A8%E4%BA%BA%E7%A1%AC%E6%8E%A7%E4%BD%8F%E4%BA%86",
          "hot": "",
          "platform": "baidu"
        },
        {
          "rank": 22,
          "title": "男子开路虎加油500元逃单 车未上牌",
          "url": "https://www.baidu.com/s?wd=%E7%94%B7%E5%AD%90%E5%BC%80%E8%B7%AF%E8%99%8E%E5%8A%A0%E6%B2%B9500%E5%85%83%E9%80%83%E5%8D%95%20%E8%BD%A6%E6%9C%AA%E4%B8%8A%E7%89%8C",
          "hot": "",
          "platform": "baidu"
        },
        {
          "rank": 23,
          "title": "常远称从新人演员身上看到了宋小宝",
          "url": "https://www.baidu.com/s?wd=%E5%B8%B8%E8%BF%9C%E7%A7%B0%E4%BB%8E%E6%96%B0%E4%BA%BA%E6%BC%94%E5%91%98%E8%BA%AB%E4%B8%8A%E7%9C%8B%E5%88%B0%E4%BA%86%E5%AE%8B%E5%B0%8F%E5%AE%9D",
          "hot": "",
          "platform": "baidu"
        },
        {
          "rank": 24,
          "title": "多次试管流产后起分歧 妻子起诉离婚",
          "url": "https://www.baidu.com/s?wd=%E5%A4%9A%E6%AC%A1%E8%AF%95%E7%AE%A1%E6%B5%81%E4%BA%A7%E5%90%8E%E8%B5%B7%E5%88%86%E6%AD%A7%20%E5%A6%BB%E5%AD%90%E8%B5%B7%E8%AF%89%E7%A6%BB%E5%A9%9A",
          "hot": "",
          "platform": "baidu"
        },
        {
          "rank": 25,
          "title": "中专生带手机入校被罚回家待到毕业",
          "url": "https://www.baidu.com/s?wd=%E4%B8%AD%E4%B8%93%E7%94%9F%E5%B8%A6%E6%89%8B%E6%9C%BA%E5%85%A5%E6%A0%A1%E8%A2%AB%E7%BD%9A%E5%9B%9E%E5%AE%B6%E5%BE%85%E5%88%B0%E6%AF%95%E4%B8%9A",
          "hot": "",
          "platform": "baidu"
        },
        {
          "rank": 26,
          "title": "武汉大暴雨破纪录",
          "url": "https://www.baidu.com/s?wd=%E6%AD%A6%E6%B1%89%E5%A4%A7%E6%9A%B4%E9%9B%A8%E7%A0%B4%E7%BA%AA%E5%BD%95",
          "hot": "",
          "platform": "baidu"
        },
        {
          "rank": 27,
          "title": "伊朗军方：已做好长期战争的准备",
          "url": "https://www.baidu.com/s?wd=%E4%BC%8A%E6%9C%97%E5%86%9B%E6%96%B9%EF%BC%9A%E5%B7%B2%E5%81%9A%E5%A5%BD%E9%95%BF%E6%9C%9F%E6%88%98%E4%BA%89%E7%9A%84%E5%87%86%E5%A4%87",
          "hot": "",
          "platform": "baidu"
        },
        {
          "rank": 28,
          "title": "黎真主党向以发射约30枚火箭弹",
          "url": "https://www.baidu.com/s?wd=%E9%BB%8E%E7%9C%9F%E4%B8%BB%E5%85%9A%E5%90%91%E4%BB%A5%E5%8F%91%E5%B0%84%E7%BA%A630%E6%9E%9A%E7%81%AB%E7%AE%AD%E5%BC%B9",
          "hot": "",
          "platform": "baidu"
        },
        {
          "rank": 29,
          "title": "59岁梁实宣布参加第30次高考",
          "url": "https://www.baidu.com/s?wd=59%E5%B2%81%E6%A2%81%E5%AE%9E%E5%AE%A3%E5%B8%83%E5%8F%82%E5%8A%A0%E7%AC%AC30%E6%AC%A1%E9%AB%98%E8%80%83",
          "hot": "",
          "platform": "baidu"
        },
        {
          "rank": 30,
          "title": "被315曝光后 美宜佳通报处置进展",
          "url": "https://www.baidu.com/s?wd=%E8%A2%AB315%E6%9B%9D%E5%85%89%E5%90%8E%20%E7%BE%8E%E5%AE%9C%E4%BD%B3%E9%80%9A%E6%8A%A5%E5%A4%84%E7%BD%AE%E8%BF%9B%E5%B1%95",
          "hot": "",
          "platform": "baidu"
        }
      ]
    },
    "toutiao": {
      "name": "今日头条",
      "icon": "📰",
      "items": [
        {
          "rank": 1,
          "title": "又一个千万人口城市要来了",
          "url": "https://www.toutiao.com/trending/7626146843453849636/?category_name=topic_innerflow&event_type=hot_board&log_pb=%7B%22category_name%22%3A%22topic_innerflow%22%2C%22cluster_type%22%3A%221%22%2C%22enter_from%22%3A%22click_category%22%2C%22entrance_hotspot%22%3A%22outside%22%2C%22event_type%22%3A%22hot_board%22%2C%22hot_board_cluster_id%22%3A%227626146843453849636%22%2C%22hot_board_impr_id%22%3A%22202604092127102CE4E0F5D5E9FCBA047C%22%2C%22jump_page%22%3A%22hot_board_page%22%2C%22location%22%3A%22news_hot_card%22%2C%22page_location%22%3A%22hot_board_page%22%2C%22source%22%3A%22trending_tab%22%2C%22style_id%22%3A%2240132%22%2C%22title%22%3A%22%E5%8F%88%E4%B8%80%E4%B8%AA%E5%8D%83%E4%B8%87%E4%BA%BA%E5%8F%A3%E5%9F%8E%E5%B8%82%E8%A6%81%E6%9D%A5%E4%BA%86%22%7D&rank=&style_id=40132&topic_id=7626146843453849636",
          "hot": "9143万",
          "platform": "toutiao"
        },
        {
          "rank": 2,
          "title": "母亲带孩子看病没钱吃饭求助店主",
          "url": "https://www.toutiao.com/trending/7626624936077033513/?category_name=topic_innerflow&event_type=hot_board&log_pb=%7B%22category_name%22%3A%22topic_innerflow%22%2C%22cluster_type%22%3A%2212%22%2C%22enter_from%22%3A%22click_category%22%2C%22entrance_hotspot%22%3A%22outside%22%2C%22event_type%22%3A%22hot_board%22%2C%22hot_board_cluster_id%22%3A%227626624936077033513%22%2C%22hot_board_impr_id%22%3A%22202604092127102CE4E0F5D5E9FCBA047C%22%2C%22jump_page%22%3A%22hot_board_page%22%2C%22location%22%3A%22news_hot_card%22%2C%22page_location%22%3A%22hot_board_page%22%2C%22source%22%3A%22trending_tab%22%2C%22style_id%22%3A%2240132%22%2C%22title%22%3A%22%E6%AF%8D%E4%BA%B2%E5%B8%A6%E5%AD%A9%E5%AD%90%E7%9C%8B%E7%97%85%E6%B2%A1%E9%92%B1%E5%90%83%E9%A5%AD%E6%B1%82%E5%8A%A9%E5%BA%97%E4%B8%BB%22%7D&rank=&style_id=40132&topic_id=7626624936077033513",
          "hot": "8273万",
          "platform": "toutiao"
        },
        {
          "rank": 3,
          "title": "“中国服务”何以乘势而上",
          "url": "https://www.toutiao.com/article/7626615942482641471",
          "hot": "7486万",
          "platform": "toutiao"
        },
        {
          "rank": 4,
          "title": "周鸿祎出席西安交大校庆后打卡小吃店",
          "url": "https://www.toutiao.com/trending/7626690054145081385/?category_name=topic_innerflow&event_type=hot_board&log_pb=%7B%22category_name%22%3A%22topic_innerflow%22%2C%22cluster_type%22%3A%220%22%2C%22enter_from%22%3A%22click_category%22%2C%22entrance_hotspot%22%3A%22outside%22%2C%22event_type%22%3A%22hot_board%22%2C%22hot_board_cluster_id%22%3A%227626690054145081385%22%2C%22hot_board_impr_id%22%3A%22202604092127102CE4E0F5D5E9FCBA047C%22%2C%22jump_page%22%3A%22hot_board_page%22%2C%22location%22%3A%22news_hot_card%22%2C%22page_location%22%3A%22hot_board_page%22%2C%22source%22%3A%22trending_tab%22%2C%22style_id%22%3A%2240132%22%2C%22title%22%3A%22%E5%91%A8%E9%B8%BF%E7%A5%8E%E5%87%BA%E5%B8%AD%E8%A5%BF%E5%AE%89%E4%BA%A4%E5%A4%A7%E6%A0%A1%E5%BA%86%E5%90%8E%E6%89%93%E5%8D%A1%E5%B0%8F%E5%90%83%E5%BA%97%22%7D&rank=&style_id=40132&topic_id=7626690054145081385",
          "hot": "6773万",
          "platform": "toutiao"
        },
        {
          "rank": 5,
          "title": "媒体谈国防部用“恶虎出笼”比喻日本",
          "url": "https://www.toutiao.com/trending/7626716626427772982/?category_name=topic_innerflow&event_type=hot_board&log_pb=%7B%22category_name%22%3A%22topic_innerflow%22%2C%22cluster_type%22%3A%220%22%2C%22enter_from%22%3A%22click_category%22%2C%22entrance_hotspot%22%3A%22outside%22%2C%22event_type%22%3A%22hot_board%22%2C%22hot_board_cluster_id%22%3A%227626716626427772982%22%2C%22hot_board_impr_id%22%3A%22202604092127102CE4E0F5D5E9FCBA047C%22%2C%22jump_page%22%3A%22hot_board_page%22%2C%22location%22%3A%22news_hot_card%22%2C%22page_location%22%3A%22hot_board_page%22%2C%22source%22%3A%22trending_tab%22%2C%22style_id%22%3A%2240132%22%2C%22title%22%3A%22%E5%AA%92%E4%BD%93%E8%B0%88%E5%9B%BD%E9%98%B2%E9%83%A8%E7%94%A8%E2%80%9C%E6%81%B6%E8%99%8E%E5%87%BA%E7%AC%BC%E2%80%9D%E6%AF%94%E5%96%BB%E6%97%A5%E6%9C%AC%22%7D&rank=&style_id=40132&topic_id=7626716626427772982",
          "hot": "6129万",
          "platform": "toutiao"
        },
        {
          "rank": 6,
          "title": "3人虚假摆拍“深山救助流浪女”被查",
          "url": "https://www.toutiao.com/trending/7626588705675038258/?category_name=topic_innerflow&event_type=hot_board&log_pb=%7B%22category_name%22%3A%22topic_innerflow%22%2C%22cluster_type%22%3A%222%22%2C%22enter_from%22%3A%22click_category%22%2C%22entrance_hotspot%22%3A%22outside%22%2C%22event_type%22%3A%22hot_board%22%2C%22hot_board_cluster_id%22%3A%227626588705675038258%22%2C%22hot_board_impr_id%22%3A%22202604092127102CE4E0F5D5E9FCBA047C%22%2C%22jump_page%22%3A%22hot_board_page%22%2C%22location%22%3A%22news_hot_card%22%2C%22page_location%22%3A%22hot_board_page%22%2C%22source%22%3A%22trending_tab%22%2C%22style_id%22%3A%2240132%22%2C%22title%22%3A%223%E4%BA%BA%E8%99%9A%E5%81%87%E6%91%86%E6%8B%8D%E2%80%9C%E6%B7%B1%E5%B1%B1%E6%95%91%E5%8A%A9%E6%B5%81%E6%B5%AA%E5%A5%B3%E2%80%9D%E8%A2%AB%E6%9F%A5%22%7D&rank=&style_id=40132&topic_id=7626588705675038258",
          "hot": "5545万",
          "platform": "toutiao"
        },
        {
          "rank": 7,
          "title": "女子连续2天吃半斤蓝莓患胃石症",
          "url": "https://www.toutiao.com/trending/7625626366440407103/?category_name=topic_innerflow&event_type=hot_board&log_pb=%7B%22category_name%22%3A%22topic_innerflow%22%2C%22cluster_type%22%3A%222%22%2C%22enter_from%22%3A%22click_category%22%2C%22entrance_hotspot%22%3A%22outside%22%2C%22event_type%22%3A%22hot_board%22%2C%22hot_board_cluster_id%22%3A%227625626366440407103%22%2C%22hot_board_impr_id%22%3A%22202604092127102CE4E0F5D5E9FCBA047C%22%2C%22jump_page%22%3A%22hot_board_page%22%2C%22location%22%3A%22news_hot_card%22%2C%22page_location%22%3A%22hot_board_page%22%2C%22source%22%3A%22trending_tab%22%2C%22style_id%22%3A%2240132%22%2C%22title%22%3A%22%E5%A5%B3%E5%AD%90%E8%BF%9E%E7%BB%AD2%E5%A4%A9%E5%90%83%E5%8D%8A%E6%96%A4%E8%93%9D%E8%8E%93%E6%82%A3%E8%83%83%E7%9F%B3%E7%97%87%22%7D&rank=&style_id=40132&topic_id=7625626366440407103",
          "hot": "5018万",
          "platform": "toutiao"
        },
        {
          "rank": 8,
          "title": "蛇爬进值班室 女子吓得夺门而出",
          "url": "https://www.toutiao.com/trending/7625966464847822867/?category_name=topic_innerflow&event_type=hot_board&log_pb=%7B%22category_name%22%3A%22topic_innerflow%22%2C%22cluster_type%22%3A%2212%22%2C%22enter_from%22%3A%22click_category%22%2C%22entrance_hotspot%22%3A%22outside%22%2C%22event_type%22%3A%22hot_board%22%2C%22hot_board_cluster_id%22%3A%227625966464847822867%22%2C%22hot_board_impr_id%22%3A%22202604092127102CE4E0F5D5E9FCBA047C%22%2C%22jump_page%22%3A%22hot_board_page%22%2C%22location%22%3A%22news_hot_card%22%2C%22page_location%22%3A%22hot_board_page%22%2C%22source%22%3A%22trending_tab%22%2C%22style_id%22%3A%2240132%22%2C%22title%22%3A%22%E8%9B%87%E7%88%AC%E8%BF%9B%E5%80%BC%E7%8F%AD%E5%AE%A4+%E5%A5%B3%E5%AD%90%E5%90%93%E5%BE%97%E5%A4%BA%E9%97%A8%E8%80%8C%E5%87%BA%22%7D&rank=&style_id=40132&topic_id=7625966464847822867",
          "hot": "4540万",
          "platform": "toutiao"
        },
        {
          "rank": 9,
          "title": "800斤黄牛坠洞4天后死亡 主人发声",
          "url": "https://www.toutiao.com/trending/7626639415583358985/?category_name=topic_innerflow&event_type=hot_board&log_pb=%7B%22category_name%22%3A%22topic_innerflow%22%2C%22cluster_type%22%3A%222%22%2C%22enter_from%22%3A%22click_category%22%2C%22entrance_hotspot%22%3A%22outside%22%2C%22event_type%22%3A%22hot_board%22%2C%22hot_board_cluster_id%22%3A%227626639415583358985%22%2C%22hot_board_impr_id%22%3A%22202604092127102CE4E0F5D5E9FCBA047C%22%2C%22jump_page%22%3A%22hot_board_page%22%2C%22location%22%3A%22news_hot_card%22%2C%22page_location%22%3A%22hot_board_page%22%2C%22source%22%3A%22trending_tab%22%2C%22style_id%22%3A%2240132%22%2C%22title%22%3A%22800%E6%96%A4%E9%BB%84%E7%89%9B%E5%9D%A0%E6%B4%9E4%E5%A4%A9%E5%90%8E%E6%AD%BB%E4%BA%A1+%E4%B8%BB%E4%BA%BA%E5%8F%91%E5%A3%B0%22%7D&rank=&style_id=40132&topic_id=7626639415583358985",
          "hot": "4108万",
          "platform": "toutiao"
        },
        {
          "rank": 10,
          "title": "女子带8万现金买手机 店长立即报警",
          "url": "https://www.toutiao.com/trending/7626660712961589254/?category_name=topic_innerflow&event_type=hot_board&log_pb=%7B%22category_name%22%3A%22topic_innerflow%22%2C%22cluster_type%22%3A%226%22%2C%22enter_from%22%3A%22click_category%22%2C%22entrance_hotspot%22%3A%22outside%22%2C%22event_type%22%3A%22hot_board%22%2C%22hot_board_cluster_id%22%3A%227626660712961589254%22%2C%22hot_board_impr_id%22%3A%22202604092127102CE4E0F5D5E9FCBA047C%22%2C%22jump_page%22%3A%22hot_board_page%22%2C%22location%22%3A%22news_hot_card%22%2C%22page_location%22%3A%22hot_board_page%22%2C%22source%22%3A%22trending_tab%22%2C%22style_id%22%3A%2240132%22%2C%22title%22%3A%22%E5%A5%B3%E5%AD%90%E5%B8%A68%E4%B8%87%E7%8E%B0%E9%87%91%E4%B9%B0%E6%89%8B%E6%9C%BA+%E5%BA%97%E9%95%BF%E7%AB%8B%E5%8D%B3%E6%8A%A5%E8%AD%A6%22%7D&rank=&style_id=40132&topic_id=7626660712961589254",
          "hot": "3717万",
          "platform": "toutiao"
        },
        {
          "rank": 11,
          "title": "点链接领“2026年度综合补贴”？别信",
          "url": "https://www.toutiao.com/trending/7626721920465243694/?category_name=topic_innerflow&event_type=hot_board&log_pb=%7B%22category_name%22%3A%22topic_innerflow%22%2C%22cluster_type%22%3A%222%22%2C%22enter_from%22%3A%22click_category%22%2C%22entrance_hotspot%22%3A%22outside%22%2C%22event_type%22%3A%22hot_board%22%2C%22hot_board_cluster_id%22%3A%227626721920465243694%22%2C%22hot_board_impr_id%22%3A%22202604092127102CE4E0F5D5E9FCBA047C%22%2C%22jump_page%22%3A%22hot_board_page%22%2C%22location%22%3A%22news_hot_card%22%2C%22page_location%22%3A%22hot_board_page%22%2C%22source%22%3A%22trending_tab%22%2C%22style_id%22%3A%2240132%22%2C%22title%22%3A%22%E7%82%B9%E9%93%BE%E6%8E%A5%E9%A2%86%E2%80%9C2026%E5%B9%B4%E5%BA%A6%E7%BB%BC%E5%90%88%E8%A1%A5%E8%B4%B4%E2%80%9D%EF%BC%9F%E5%88%AB%E4%BF%A1%22%7D&rank=&style_id=40132&topic_id=7626721920465243694",
          "hot": "3363万",
          "platform": "toutiao"
        },
        {
          "rank": 12,
          "title": "文章开饭店了",
          "url": "https://www.toutiao.com/trending/7626207096480186410/?category_name=topic_innerflow&event_type=hot_board&log_pb=%7B%22category_name%22%3A%22topic_innerflow%22%2C%22cluster_type%22%3A%222%22%2C%22enter_from%22%3A%22click_category%22%2C%22entrance_hotspot%22%3A%22outside%22%2C%22event_type%22%3A%22hot_board%22%2C%22hot_board_cluster_id%22%3A%227626207096480186410%22%2C%22hot_board_impr_id%22%3A%22202604092127102CE4E0F5D5E9FCBA047C%22%2C%22jump_page%22%3A%22hot_board_page%22%2C%22location%22%3A%22news_hot_card%22%2C%22page_location%22%3A%22hot_board_page%22%2C%22source%22%3A%22trending_tab%22%2C%22style_id%22%3A%2240132%22%2C%22title%22%3A%22%E6%96%87%E7%AB%A0%E5%BC%80%E9%A5%AD%E5%BA%97%E4%BA%86%22%7D&rank=&style_id=40132&topic_id=7626207096480186410",
          "hot": "3043万",
          "platform": "toutiao"
        },
        {
          "rank": 13,
          "title": "中方回应美对向伊供武国家征50%关税",
          "url": "https://www.toutiao.com/trending/7626356839189577766/?category_name=topic_innerflow&event_type=hot_board&log_pb=%7B%22category_name%22%3A%22topic_innerflow%22%2C%22cluster_type%22%3A%222%22%2C%22enter_from%22%3A%22click_category%22%2C%22entrance_hotspot%22%3A%22outside%22%2C%22event_type%22%3A%22hot_board%22%2C%22hot_board_cluster_id%22%3A%227626356839189577766%22%2C%22hot_board_impr_id%22%3A%22202604092127102CE4E0F5D5E9FCBA047C%22%2C%22jump_page%22%3A%22hot_board_page%22%2C%22location%22%3A%22news_hot_card%22%2C%22page_location%22%3A%22hot_board_page%22%2C%22source%22%3A%22trending_tab%22%2C%22style_id%22%3A%2240132%22%2C%22title%22%3A%22%E4%B8%AD%E6%96%B9%E5%9B%9E%E5%BA%94%E7%BE%8E%E5%AF%B9%E5%90%91%E4%BC%8A%E4%BE%9B%E6%AD%A6%E5%9B%BD%E5%AE%B6%E5%BE%8150%25%E5%85%B3%E7%A8%8E%22%7D&rank=&style_id=40132&topic_id=7626356839189577766",
          "hot": "2753万",
          "platform": "toutiao"
        },
        {
          "rank": 14,
          "title": "伊朗革命卫队：复仇不会停止",
          "url": "https://www.toutiao.com/trending/7626711314328587802/?category_name=topic_innerflow&event_type=hot_board&log_pb=%7B%22category_name%22%3A%22topic_innerflow%22%2C%22cluster_type%22%3A%222%22%2C%22enter_from%22%3A%22click_category%22%2C%22entrance_hotspot%22%3A%22outside%22%2C%22event_type%22%3A%22hot_board%22%2C%22hot_board_cluster_id%22%3A%227626711314328587802%22%2C%22hot_board_impr_id%22%3A%22202604092127102CE4E0F5D5E9FCBA047C%22%2C%22jump_page%22%3A%22hot_board_page%22%2C%22location%22%3A%22news_hot_card%22%2C%22page_location%22%3A%22hot_board_page%22%2C%22source%22%3A%22trending_tab%22%2C%22style_id%22%3A%2240132%22%2C%22title%22%3A%22%E4%BC%8A%E6%9C%97%E9%9D%A9%E5%91%BD%E5%8D%AB%E9%98%9F%EF%BC%9A%E5%A4%8D%E4%BB%87%E4%B8%8D%E4%BC%9A%E5%81%9C%E6%AD%A2%22%7D&rank=&style_id=40132&topic_id=7626711314328587802",
          "hot": "2491万",
          "platform": "toutiao"
        },
        {
          "rank": 15,
          "title": "你心中的NBA最佳阵容都有谁",
          "url": "https://www.toutiao.com/trending/7626371675835367466/?category_name=topic_innerflow&event_type=hot_board&log_pb=%7B%22category_name%22%3A%22topic_innerflow%22%2C%22cluster_type%22%3A%2210%22%2C%22enter_from%22%3A%22click_category%22%2C%22entrance_hotspot%22%3A%22outside%22%2C%22event_type%22%3A%22hot_board%22%2C%22hot_board_cluster_id%22%3A%227626371675835367466%22%2C%22hot_board_impr_id%22%3A%22202604092127102CE4E0F5D5E9FCBA047C%22%2C%22jump_page%22%3A%22hot_board_page%22%2C%22location%22%3A%22news_hot_card%22%2C%22page_location%22%3A%22hot_board_page%22%2C%22source%22%3A%22trending_tab%22%2C%22style_id%22%3A%2240132%22%2C%22title%22%3A%22%E4%BD%A0%E5%BF%83%E4%B8%AD%E7%9A%84NBA%E6%9C%80%E4%BD%B3%E9%98%B5%E5%AE%B9%E9%83%BD%E6%9C%89%E8%B0%81%22%7D&rank=&style_id=40132&topic_id=7626371675835367466",
          "hot": "2254万",
          "platform": "toutiao"
        },
        {
          "rank": 16,
          "title": "如何成功戒酒",
          "url": "https://www.toutiao.com/trending/7626402184499216434/?category_name=topic_innerflow&event_type=hot_board&log_pb=%7B%22category_name%22%3A%22topic_innerflow%22%2C%22cluster_type%22%3A%2210%22%2C%22enter_from%22%3A%22click_category%22%2C%22entrance_hotspot%22%3A%22outside%22%2C%22event_type%22%3A%22hot_board%22%2C%22hot_board_cluster_id%22%3A%227626402184499216434%22%2C%22hot_board_impr_id%22%3A%22202604092127102CE4E0F5D5E9FCBA047C%22%2C%22jump_page%22%3A%22hot_board_page%22%2C%22location%22%3A%22news_hot_card%22%2C%22page_location%22%3A%22hot_board_page%22%2C%22source%22%3A%22trending_tab%22%2C%22style_id%22%3A%2240132%22%2C%22title%22%3A%22%E5%A6%82%E4%BD%95%E6%88%90%E5%8A%9F%E6%88%92%E9%85%92%22%7D&rank=&style_id=40132&topic_id=7626402184499216434",
          "hot": "2040万",
          "platform": "toutiao"
        },
        {
          "rank": 17,
          "title": "伊朗战事真的停火了吗",
          "url": "https://www.toutiao.com/trending/7626716353449168393/?category_name=topic_innerflow&event_type=hot_board&log_pb=%7B%22category_name%22%3A%22topic_innerflow%22%2C%22cluster_type%22%3A%2213%22%2C%22enter_from%22%3A%22click_category%22%2C%22entrance_hotspot%22%3A%22outside%22%2C%22event_type%22%3A%22hot_board%22%2C%22hot_board_cluster_id%22%3A%227626716353449168393%22%2C%22hot_board_impr_id%22%3A%22202604092127102CE4E0F5D5E9FCBA047C%22%2C%22jump_page%22%3A%22hot_board_page%22%2C%22location%22%3A%22news_hot_card%22%2C%22page_location%22%3A%22hot_board_page%22%2C%22source%22%3A%22trending_tab%22%2C%22style_id%22%3A%2240132%22%2C%22title%22%3A%22%E4%BC%8A%E6%9C%97%E6%88%98%E4%BA%8B%E7%9C%9F%E7%9A%84%E5%81%9C%E7%81%AB%E4%BA%86%E5%90%97%22%7D&rank=&style_id=40132&topic_id=7626716353449168393",
          "hot": "1846万",
          "platform": "toutiao"
        },
        {
          "rank": 18,
          "title": "沈腾马丽握手瞬间双双绷不住了",
          "url": "https://www.toutiao.com/trending/7626535281260380196/?category_name=topic_innerflow&event_type=hot_board&log_pb=%7B%22category_name%22%3A%22topic_innerflow%22%2C%22cluster_type%22%3A%228%22%2C%22enter_from%22%3A%22click_category%22%2C%22entrance_hotspot%22%3A%22outside%22%2C%22event_type%22%3A%22hot_board%22%2C%22hot_board_cluster_id%22%3A%227626535281260380196%22%2C%22hot_board_impr_id%22%3A%22202604092127102CE4E0F5D5E9FCBA047C%22%2C%22jump_page%22%3A%22hot_board_page%22%2C%22location%22%3A%22news_hot_card%22%2C%22page_location%22%3A%22hot_board_page%22%2C%22source%22%3A%22trending_tab%22%2C%22style_id%22%3A%2240132%22%2C%22title%22%3A%22%E6%B2%88%E8%85%BE%E9%A9%AC%E4%B8%BD%E6%8F%A1%E6%89%8B%E7%9E%AC%E9%97%B4%E5%8F%8C%E5%8F%8C%E7%BB%B7%E4%B8%8D%E4%BD%8F%E4%BA%86%22%7D&rank=&style_id=40132&topic_id=7626535281260380196",
          "hot": "1670万",
          "platform": "toutiao"
        },
        {
          "rank": 19,
          "title": "伊朗称国内总体已恢复正常秩序",
          "url": "https://www.toutiao.com/trending/7626017343296569353/?category_name=topic_innerflow&event_type=hot_board&log_pb=%7B%22category_name%22%3A%22topic_innerflow%22%2C%22cluster_type%22%3A%226%22%2C%22enter_from%22%3A%22click_category%22%2C%22entrance_hotspot%22%3A%22outside%22%2C%22event_type%22%3A%22hot_board%22%2C%22hot_board_cluster_id%22%3A%227626017343296569353%22%2C%22hot_board_impr_id%22%3A%22202604092127102CE4E0F5D5E9FCBA047C%22%2C%22jump_page%22%3A%22hot_board_page%22%2C%22location%22%3A%22news_hot_card%22%2C%22page_location%22%3A%22hot_board_page%22%2C%22source%22%3A%22trending_tab%22%2C%22style_id%22%3A%2240132%22%2C%22title%22%3A%22%E4%BC%8A%E6%9C%97%E7%A7%B0%E5%9B%BD%E5%86%85%E6%80%BB%E4%BD%93%E5%B7%B2%E6%81%A2%E5%A4%8D%E6%AD%A3%E5%B8%B8%E7%A7%A9%E5%BA%8F%22%7D&rank=&style_id=40132&topic_id=7626017343296569353",
          "hot": "1511万",
          "platform": "toutiao"
        },
        {
          "rank": 20,
          "title": "记者直击武汉暴雨",
          "url": "https://www.toutiao.com/trending/7626597059180658751/?category_name=topic_innerflow&event_type=hot_board&log_pb=%7B%22category_name%22%3A%22topic_innerflow%22%2C%22cluster_type%22%3A%226%22%2C%22enter_from%22%3A%22click_category%22%2C%22entrance_hotspot%22%3A%22outside%22%2C%22event_type%22%3A%22hot_board%22%2C%22hot_board_cluster_id%22%3A%227626597059180658751%22%2C%22hot_board_impr_id%22%3A%22202604092127102CE4E0F5D5E9FCBA047C%22%2C%22jump_page%22%3A%22hot_board_page%22%2C%22location%22%3A%22news_hot_card%22%2C%22page_location%22%3A%22hot_board_page%22%2C%22source%22%3A%22trending_tab%22%2C%22style_id%22%3A%2240132%22%2C%22title%22%3A%22%E8%AE%B0%E8%80%85%E7%9B%B4%E5%87%BB%E6%AD%A6%E6%B1%89%E6%9A%B4%E9%9B%A8%22%7D&rank=&style_id=40132&topic_id=7626597059180658751",
          "hot": "1367万",
          "platform": "toutiao"
        },
        {
          "rank": 21,
          "title": "NASA发布有史以来最清晰月球照",
          "url": "https://www.toutiao.com/trending/7626135639670472746/?category_name=topic_innerflow&event_type=hot_board&log_pb=%7B%22category_name%22%3A%22topic_innerflow%22%2C%22cluster_type%22%3A%221%22%2C%22enter_from%22%3A%22click_category%22%2C%22entrance_hotspot%22%3A%22outside%22%2C%22event_type%22%3A%22hot_board%22%2C%22hot_board_cluster_id%22%3A%227626135639670472746%22%2C%22hot_board_impr_id%22%3A%22202604092127102CE4E0F5D5E9FCBA047C%22%2C%22jump_page%22%3A%22hot_board_page%22%2C%22location%22%3A%22news_hot_card%22%2C%22page_location%22%3A%22hot_board_page%22%2C%22source%22%3A%22trending_tab%22%2C%22style_id%22%3A%2240132%22%2C%22title%22%3A%22NASA%E5%8F%91%E5%B8%83%E6%9C%89%E5%8F%B2%E4%BB%A5%E6%9D%A5%E6%9C%80%E6%B8%85%E6%99%B0%E6%9C%88%E7%90%83%E7%85%A7%22%7D&rank=&style_id=40132&topic_id=7626135639670472746",
          "hot": "1237万",
          "platform": "toutiao"
        },
        {
          "rank": 22,
          "title": "95后小伙在村里清淤引300万网友围观",
          "url": "https://www.toutiao.com/trending/7625883961562120246/?category_name=topic_innerflow&event_type=hot_board&log_pb=%7B%22category_name%22%3A%22topic_innerflow%22%2C%22cluster_type%22%3A%226%22%2C%22enter_from%22%3A%22click_category%22%2C%22entrance_hotspot%22%3A%22outside%22%2C%22event_type%22%3A%22hot_board%22%2C%22hot_board_cluster_id%22%3A%227625883961562120246%22%2C%22hot_board_impr_id%22%3A%22202604092127102CE4E0F5D5E9FCBA047C%22%2C%22jump_page%22%3A%22hot_board_page%22%2C%22location%22%3A%22news_hot_card%22%2C%22page_location%22%3A%22hot_board_page%22%2C%22source%22%3A%22trending_tab%22%2C%22style_id%22%3A%2240132%22%2C%22title%22%3A%2295%E5%90%8E%E5%B0%8F%E4%BC%99%E5%9C%A8%E6%9D%91%E9%87%8C%E6%B8%85%E6%B7%A4%E5%BC%95300%E4%B8%87%E7%BD%91%E5%8F%8B%E5%9B%B4%E8%A7%82%22%7D&rank=&style_id=40132&topic_id=7625883961562120246",
          "hot": "1119万",
          "platform": "toutiao"
        },
        {
          "rank": 23,
          "title": "刘强东章泽天成立新公司",
          "url": "https://www.toutiao.com/trending/7626423986808946730/?category_name=topic_innerflow&event_type=hot_board&log_pb=%7B%22category_name%22%3A%22topic_innerflow%22%2C%22cluster_type%22%3A%220%22%2C%22enter_from%22%3A%22click_category%22%2C%22entrance_hotspot%22%3A%22outside%22%2C%22event_type%22%3A%22hot_board%22%2C%22hot_board_cluster_id%22%3A%227626423986808946730%22%2C%22hot_board_impr_id%22%3A%22202604092127102CE4E0F5D5E9FCBA047C%22%2C%22jump_page%22%3A%22hot_board_page%22%2C%22location%22%3A%22news_hot_card%22%2C%22page_location%22%3A%22hot_board_page%22%2C%22source%22%3A%22trending_tab%22%2C%22style_id%22%3A%2240132%22%2C%22title%22%3A%22%E5%88%98%E5%BC%BA%E4%B8%9C%E7%AB%A0%E6%B3%BD%E5%A4%A9%E6%88%90%E7%AB%8B%E6%96%B0%E5%85%AC%E5%8F%B8%22%7D&rank=&style_id=40132&topic_id=7626423986808946730",
          "hot": "1013万",
          "platform": "toutiao"
        },
        {
          "rank": 24,
          "title": "35岁孕妇吃冰箱剩菜后去世",
          "url": "https://www.toutiao.com/trending/7626592436416806975/?category_name=topic_innerflow&event_type=hot_board&log_pb=%7B%22category_name%22%3A%22topic_innerflow%22%2C%22cluster_type%22%3A%228%22%2C%22enter_from%22%3A%22click_category%22%2C%22entrance_hotspot%22%3A%22outside%22%2C%22event_type%22%3A%22hot_board%22%2C%22hot_board_cluster_id%22%3A%227626592436416806975%22%2C%22hot_board_impr_id%22%3A%22202604092127102CE4E0F5D5E9FCBA047C%22%2C%22jump_page%22%3A%22hot_board_page%22%2C%22location%22%3A%22news_hot_card%22%2C%22page_location%22%3A%22hot_board_page%22%2C%22source%22%3A%22trending_tab%22%2C%22style_id%22%3A%2240132%22%2C%22title%22%3A%2235%E5%B2%81%E5%AD%95%E5%A6%87%E5%90%83%E5%86%B0%E7%AE%B1%E5%89%A9%E8%8F%9C%E5%90%8E%E5%8E%BB%E4%B8%96%22%7D&rank=&style_id=40132&topic_id=7626592436416806975",
          "hot": "916万",
          "platform": "toutiao"
        },
        {
          "rank": 25,
          "title": "武汉迎暴雨降下鹌鹑蛋大冰雹",
          "url": "https://www.toutiao.com/trending/7626270675593855019/?category_name=topic_innerflow&event_type=hot_board&log_pb=%7B%22category_name%22%3A%22topic_innerflow%22%2C%22cluster_type%22%3A%221%22%2C%22enter_from%22%3A%22click_category%22%2C%22entrance_hotspot%22%3A%22outside%22%2C%22event_type%22%3A%22hot_board%22%2C%22hot_board_cluster_id%22%3A%227626270675593855019%22%2C%22hot_board_impr_id%22%3A%22202604092127102CE4E0F5D5E9FCBA047C%22%2C%22jump_page%22%3A%22hot_board_page%22%2C%22location%22%3A%22news_hot_card%22%2C%22page_location%22%3A%22hot_board_page%22%2C%22source%22%3A%22trending_tab%22%2C%22style_id%22%3A%2240132%22%2C%22title%22%3A%22%E6%AD%A6%E6%B1%89%E8%BF%8E%E6%9A%B4%E9%9B%A8%E9%99%8D%E4%B8%8B%E9%B9%8C%E9%B9%91%E8%9B%8B%E5%A4%A7%E5%86%B0%E9%9B%B9%22%7D&rank=&style_id=40132&topic_id=7626270675593855019",
          "hot": "829万",
          "platform": "toutiao"
        },
        {
          "rank": 26,
          "title": "伊朗军方称已做好长期战争的准备",
          "url": "https://www.toutiao.com/trending/7626158420348944422/?category_name=topic_innerflow&event_type=hot_board&log_pb=%7B%22category_name%22%3A%22topic_innerflow%22%2C%22cluster_type%22%3A%222%22%2C%22enter_from%22%3A%22click_category%22%2C%22entrance_hotspot%22%3A%22outside%22%2C%22event_type%22%3A%22hot_board%22%2C%22hot_board_cluster_id%22%3A%227626158420348944422%22%2C%22hot_board_impr_id%22%3A%22202604092127102CE4E0F5D5E9FCBA047C%22%2C%22jump_page%22%3A%22hot_board_page%22%2C%22location%22%3A%22news_hot_card%22%2C%22page_location%22%3A%22hot_board_page%22%2C%22source%22%3A%22trending_tab%22%2C%22style_id%22%3A%2240132%22%2C%22title%22%3A%22%E4%BC%8A%E6%9C%97%E5%86%9B%E6%96%B9%E7%A7%B0%E5%B7%B2%E5%81%9A%E5%A5%BD%E9%95%BF%E6%9C%9F%E6%88%98%E4%BA%89%E7%9A%84%E5%87%86%E5%A4%87%22%7D&rank=&style_id=40132&topic_id=7626158420348944422",
          "hot": "750万",
          "platform": "toutiao"
        },
        {
          "rank": 27,
          "title": "正直播CBA焦点战：山西vs深圳",
          "url": "https://www.toutiao.com/trending/7626317812579208747/?category_name=topic_innerflow&event_type=hot_board&log_pb=%7B%22category_name%22%3A%22topic_innerflow%22%2C%22cluster_type%22%3A%222%22%2C%22enter_from%22%3A%22click_category%22%2C%22entrance_hotspot%22%3A%22outside%22%2C%22event_type%22%3A%22hot_board%22%2C%22hot_board_cluster_id%22%3A%227626317812579208747%22%2C%22hot_board_impr_id%22%3A%22202604092127102CE4E0F5D5E9FCBA047C%22%2C%22jump_page%22%3A%22hot_board_page%22%2C%22location%22%3A%22news_hot_card%22%2C%22page_location%22%3A%22hot_board_page%22%2C%22source%22%3A%22trending_tab%22%2C%22style_id%22%3A%2240132%22%2C%22title%22%3A%22%E6%AD%A3%E7%9B%B4%E6%92%ADCBA%E7%84%A6%E7%82%B9%E6%88%98%EF%BC%9A%E5%B1%B1%E8%A5%BFvs%E6%B7%B1%E5%9C%B3%22%7D&rank=&style_id=40132&topic_id=7626317812579208747",
          "hot": "679万",
          "platform": "toutiao"
        },
        {
          "rank": 28,
          "title": "俄乌进行新一轮阵亡军人遗体交换",
          "url": "https://www.toutiao.com/trending/7626318539168251940/?category_name=topic_innerflow&event_type=hot_board&log_pb=%7B%22category_name%22%3A%22topic_innerflow%22%2C%22cluster_type%22%3A%226%22%2C%22enter_from%22%3A%22click_category%22%2C%22entrance_hotspot%22%3A%22outside%22%2C%22event_type%22%3A%22hot_board%22%2C%22hot_board_cluster_id%22%3A%227626318539168251940%22%2C%22hot_board_impr_id%22%3A%22202604092127102CE4E0F5D5E9FCBA047C%22%2C%22jump_page%22%3A%22hot_board_page%22%2C%22location%22%3A%22news_hot_card%22%2C%22page_location%22%3A%22hot_board_page%22%2C%22source%22%3A%22trending_tab%22%2C%22style_id%22%3A%2240132%22%2C%22title%22%3A%22%E4%BF%84%E4%B9%8C%E8%BF%9B%E8%A1%8C%E6%96%B0%E4%B8%80%E8%BD%AE%E9%98%B5%E4%BA%A1%E5%86%9B%E4%BA%BA%E9%81%97%E4%BD%93%E4%BA%A4%E6%8D%A2%22%7D&rank=&style_id=40132&topic_id=7626318539168251940",
          "hot": "614万",
          "platform": "toutiao"
        },
        {
          "rank": 29,
          "title": "租客用水泥封死全屋7个下水道",
          "url": "https://www.toutiao.com/trending/7626649899030937654/?category_name=topic_innerflow&event_type=hot_board&log_pb=%7B%22category_name%22%3A%22topic_innerflow%22%2C%22cluster_type%22%3A%226%22%2C%22enter_from%22%3A%22click_category%22%2C%22entrance_hotspot%22%3A%22outside%22%2C%22event_type%22%3A%22hot_board%22%2C%22hot_board_cluster_id%22%3A%227626649899030937654%22%2C%22hot_board_impr_id%22%3A%22202604092127102CE4E0F5D5E9FCBA047C%22%2C%22jump_page%22%3A%22hot_board_page%22%2C%22location%22%3A%22news_hot_card%22%2C%22page_location%22%3A%22hot_board_page%22%2C%22source%22%3A%22trending_tab%22%2C%22style_id%22%3A%2240132%22%2C%22title%22%3A%22%E7%A7%9F%E5%AE%A2%E7%94%A8%E6%B0%B4%E6%B3%A5%E5%B0%81%E6%AD%BB%E5%85%A8%E5%B1%8B7%E4%B8%AA%E4%B8%8B%E6%B0%B4%E9%81%93%22%7D&rank=&style_id=40132&topic_id=7626649899030937654",
          "hot": "556万",
          "platform": "toutiao"
        },
        {
          "rank": 30,
          "title": "央视曝光黑中医馆骗局",
          "url": "https://www.toutiao.com/trending/7626596952947478062/?category_name=topic_innerflow&event_type=hot_board&log_pb=%7B%22category_name%22%3A%22topic_innerflow%22%2C%22cluster_type%22%3A%221%22%2C%22enter_from%22%3A%22click_category%22%2C%22entrance_hotspot%22%3A%22outside%22%2C%22event_type%22%3A%22hot_board%22%2C%22hot_board_cluster_id%22%3A%227626596952947478062%22%2C%22hot_board_impr_id%22%3A%22202604092127102CE4E0F5D5E9FCBA047C%22%2C%22jump_page%22%3A%22hot_board_page%22%2C%22location%22%3A%22news_hot_card%22%2C%22page_location%22%3A%22hot_board_page%22%2C%22source%22%3A%22trending_tab%22%2C%22style_id%22%3A%2240132%22%2C%22title%22%3A%22%E5%A4%AE%E8%A7%86%E6%9B%9D%E5%85%89%E9%BB%91%E4%B8%AD%E5%8C%BB%E9%A6%86%E9%AA%97%E5%B1%80%22%7D&rank=&style_id=40132&topic_id=7626596952947478062",
          "hot": "503万",
          "platform": "toutiao"
        }
      ]
    }
  }
}